hs_httpController/CurlHttpController.py
hs_httpController/__init__.py
hs_logController/LogController.py
hs_logController/__init__.py
hs_package-0.0.7.dist-info/METADATA
hs_package-0.0.7.dist-info/WHEEL
hs_package-0.0.7.dist-info/top_level.txt
hs_package-0.0.7.dist-info/RECORD
