Metadata-Version: 2.1
Name: hs-package
Version: 0.0.7
Summary: hs_httpController provides http protocol network request
Requires-Dist: pycurl
Requires-Dist: redis
Requires-Dist: kafka
Requires-Dist: logging
